{
  "last_checked": "2026-04-17T05:18:03.135335+00:00",
  "checked_releases": [
    {
      "tag": "xpi",
      "published_at": "2026-01-26T10:06:29Z",
      "xpi_asset_id": 346019754,
      "xpi_name": "pdf-ai-bookmarks.xpi",
      "xpi_download_url": "https://github.com/edwintuan/pdf-ai-bookmarks/releases/download/xpi/pdf-ai-bookmarks.xpi",
      "addon_id": "pdf-ai-bookmarks@edwintuan.com",
      "addon_name": "PDF AI Bookmarks",
      "addon_version": "1.0.0",
      "addon_description": "Generate AI-powered bookmarks for PDFs using Gemini.",
      "min_zotero_version": "7.0",
      "max_zotero_version": "8.*",
      "update_url": "https://github.com/edwintuan/pdf-ai-bookmarks/releases/download/xpi/pdf-ai-bookmarks.xpi",
      "parse_success": true
    },
    {
      "tag": "1.0.2",
      "published_at": "2026-04-17T01:09:18Z",
      "xpi_asset_id": 398203767,
      "xpi_name": "pdf-ai-bookmarks-1.0.2.xpi",
      "xpi_download_url": "https://github.com/edwintuan/pdf-ai-bookmarks/releases/download/1.0.2/pdf-ai-bookmarks-1.0.2.xpi",
      "addon_id": "pdf-ai-bookmarks@edwintuan.com",
      "addon_name": "PDF AI Bookmarks",
      "addon_version": "1.0.2",
      "addon_description": "Generate AI-powered bookmarks for PDFs using Gemini.",
      "min_zotero_version": "8.0",
      "max_zotero_version": "9.*",
      "update_url": "https://raw.githubusercontent.com/edwintuan/pdf-ai-bookmarks/main/update.json",
      "parse_success": true
    }
  ]
}