{
  "last_checked": "2025-12-24T02:30:28.773441+00:00",
  "checked_releases": [
    {
      "tag": "0.95.6",
      "published_at": "2022-12-10T09:00:41Z",
      "xpi_asset_id": 87685183,
      "xpi_name": "zotero-updateifs.xpi",
      "xpi_download_url": "https://github.com/redleafnew/zotero-updateifs/releases/download/0.95.6/zotero-updateifs.xpi",
      "addon_id": "zoteroupdateifs@redleafnew.me",
      "addon_name": "Zotero Update IFs",
      "addon_version": "0.95.6",
      "addon_description": "Zotero plugin for update IF from http://sci.justscience.cn/",
      "min_zotero_version": "3.0b1",
      "max_zotero_version": "6.*",
      "parse_success": true
    },
    {
      "tag": "0.95.5",
      "published_at": "2022-12-10T08:00:56Z",
      "xpi_asset_id": 87682107,
      "xpi_name": "zotero-updateifs.xpi",
      "xpi_download_url": "https://github.com/redleafnew/zotero-updateifs/releases/download/0.95.5/zotero-updateifs.xpi",
      "addon_id": "zoteroupdateifs@redleafnew.me",
      "addon_name": "Zotero Update IFs",
      "addon_version": "0.95.5",
      "addon_description": "Zotero plugin for update IF from http://sci.justscience.cn/",
      "min_zotero_version": "3.0b1",
      "max_zotero_version": "6.*",
      "parse_success": true
    },
    {
      "tag": "0.95.4",
      "published_at": "2022-12-03T06:54:36Z",
      "xpi_asset_id": 86841068,
      "xpi_name": "zotero-updateifs.xpi",
      "xpi_download_url": "https://github.com/redleafnew/zotero-updateifs/releases/download/0.95.4/zotero-updateifs.xpi",
      "addon_id": "zoteroupdateifs@redleafnew.me",
      "addon_name": "Zotero Update IFs",
      "addon_version": "0.95.4",
      "addon_description": "Zotero plugin for update IF from http://sci.justscience.cn/",
      "min_zotero_version": "3.0b1",
      "max_zotero_version": "6.*",
      "parse_success": true
    },
    {
      "tag": "0.95.3",
      "published_at": "2022-12-03T04:06:18Z",
      "xpi_asset_id": 86829773,
      "xpi_name": "zotero-updateifs.xpi",
      "xpi_download_url": "https://github.com/redleafnew/zotero-updateifs/releases/download/0.95.3/zotero-updateifs.xpi",
      "addon_id": "zoteroupdateifs@redleafnew.me",
      "addon_name": "Zotero Update IFs",
      "addon_version": "0.95.3",
      "addon_description": "Zotero plugin for update IF from http://sci.justscience.cn/",
      "min_zotero_version": "3.0b1",
      "max_zotero_version": "6.*",
      "parse_success": true
    },
    {
      "tag": "0.95.2",
      "published_at": "2022-11-26T14:22:27Z",
      "xpi_asset_id": 86039105,
      "xpi_name": "zotero-updateifs.xpi",
      "xpi_download_url": "https://github.com/redleafnew/zotero-updateifs/releases/download/0.95.2/zotero-updateifs.xpi",
      "addon_id": "zoteroupdateifs@redleafnew.me",
      "addon_name": "Zotero Update IFs",
      "addon_version": "0.95.2",
      "addon_description": "Zotero plugin for update IF from http://sci.justscience.cn/",
      "min_zotero_version": "3.0b1",
      "max_zotero_version": "6.*",
      "parse_success": true
    },
    {
      "tag": "0.95.1",
      "published_at": "2022-11-26T13:09:27Z",
      "xpi_asset_id": 86035271,
      "xpi_name": "zotero-updateifs.xpi",
      "xpi_download_url": "https://github.com/redleafnew/zotero-updateifs/releases/download/0.95.1/zotero-updateifs.xpi",
      "addon_id": "zoteroupdateifs@redleafnew.me",
      "addon_name": "Zotero Update IFs",
      "addon_version": "0.95.1",
      "addon_description": "Zotero plugin for update IF from http://sci.justscience.cn/",
      "min_zotero_version": "3.0b1",
      "max_zotero_version": "6.*",
      "parse_success": true
    },
    {
      "tag": "0.95.0",
      "published_at": "2022-11-25T03:41:16Z",
      "xpi_asset_id": 85891571,
      "xpi_name": "zotero-updateifs.xpi",
      "xpi_download_url": "https://github.com/redleafnew/zotero-updateifs/releases/download/0.95.0/zotero-updateifs.xpi",
      "addon_id": "zoteroupdateifs@redleafnew.me",
      "addon_name": "Zotero Update IFs",
      "addon_version": "0.95.0",
      "addon_description": "Zotero plugin for update IF from http://sci.justscience.cn/",
      "min_zotero_version": "3.0b1",
      "max_zotero_version": "6.*",
      "parse_success": true
    },
    {
      "tag": "0.94.5",
      "published_at": "2022-10-26T14:30:23Z",
      "xpi_asset_id": 82341177,
      "xpi_name": "zotero-updateifs.xpi",
      "xpi_download_url": "https://github.com/redleafnew/zotero-updateifs/releases/download/0.94.5/zotero-updateifs.xpi",
      "addon_id": "zoteroupdateifs@redleafnew.me",
      "addon_name": "Zotero Update IFs",
      "addon_version": "0.94.5",
      "addon_description": "Zotero plugin for update IF from http://sci.justscience.cn/",
      "min_zotero_version": "3.0b1",
      "max_zotero_version": "6.*",
      "parse_success": true
    },
    {
      "tag": "0.94",
      "published_at": "2022-10-25T13:21:45Z",
      "xpi_asset_id": 82208266,
      "xpi_name": "zotero-updateifs.xpi",
      "xpi_download_url": "https://github.com/redleafnew/zotero-updateifs/releases/download/0.94/zotero-updateifs.xpi",
      "addon_id": "zoteroupdateifs@redleafnew.me",
      "addon_name": "Zotero Update IFs",
      "addon_version": "0.94",
      "addon_description": "Zotero plugin for update IF from http://sci.justscience.cn/",
      "min_zotero_version": "3.0b1",
      "max_zotero_version": "6.*",
      "parse_success": true
    },
    {
      "tag": "0.93.5",
      "published_at": "2022-07-24T12:10:24Z",
      "xpi_asset_id": 72529543,
      "xpi_name": "zotero-updateifs.xpi",
      "xpi_download_url": "https://github.com/redleafnew/zotero-updateifs/releases/download/0.93.5/zotero-updateifs.xpi",
      "addon_id": "zoteroupdateifs@redleafnew.me",
      "addon_name": "Zotero Update IFs",
      "addon_version": "0.93.5",
      "addon_description": "Zotero plugin for update IF from http://sci.justscience.cn/",
      "min_zotero_version": "3.0b1",
      "max_zotero_version": "6.*",
      "parse_success": true
    },
    {
      "tag": "0.93.0",
      "published_at": "2022-05-17T00:42:32Z",
      "xpi_asset_id": 65729366,
      "xpi_name": "zotero-updateifs.xpi",
      "xpi_download_url": "https://github.com/redleafnew/zotero-updateifs/releases/download/0.93.0/zotero-updateifs.xpi",
      "addon_id": "zoteroupdateifs@redleafnew.me",
      "addon_name": "Zotero Update IFs",
      "addon_version": "0.93.0",
      "addon_description": "Zotero plugin for update IF from http://sci.justscience.cn/",
      "min_zotero_version": "3.0b1",
      "max_zotero_version": "6.*",
      "parse_success": true
    },
    {
      "tag": "0.92.1",
      "published_at": "2022-05-09T09:26:06Z",
      "xpi_asset_id": 64925337,
      "xpi_name": "zotero-updateifs.xpi",
      "xpi_download_url": "https://github.com/redleafnew/zotero-updateifs/releases/download/0.92.1/zotero-updateifs.xpi",
      "addon_id": "zoteroupdateifs@redleafnew.me",
      "addon_name": "Zotero Update IFs",
      "addon_version": "0.92.1",
      "addon_description": "Zotero plugin for update IF from http://sci.justscience.cn/",
      "min_zotero_version": "3.0b1",
      "max_zotero_version": "6.*",
      "parse_success": true
    },
    {
      "tag": "0.92.0",
      "published_at": "2022-04-15T12:32:55Z",
      "xpi_asset_id": 62669038,
      "xpi_name": "zotero-updateifs.xpi",
      "xpi_download_url": "https://github.com/redleafnew/zotero-updateifs/releases/download/0.92.0/zotero-updateifs.xpi",
      "addon_id": "zoteroupdateifs@redleafnew.me",
      "addon_name": "Zotero Update IFs",
      "addon_version": "0.92.0",
      "addon_description": "Zotero plugin for update IF from http://sci.justscience.cn/",
      "min_zotero_version": "3.0b1",
      "max_zotero_version": "6.*",
      "parse_success": true
    },
    {
      "tag": "0.91.1",
      "published_at": "2022-04-14T09:37:21Z",
      "xpi_asset_id": 62551140,
      "xpi_name": "zotero-updateifs.xpi",
      "xpi_download_url": "https://github.com/redleafnew/zotero-updateifs/releases/download/0.91.1/zotero-updateifs.xpi",
      "addon_id": "zoteroupdateifs@redleafnew.me",
      "addon_name": "Zotero Update IFs",
      "addon_version": "0.91.1",
      "addon_description": "Zotero plugin for update IF from http://sci.justscience.cn/",
      "min_zotero_version": "3.0b1",
      "max_zotero_version": "6.*",
      "parse_success": true
    },
    {
      "tag": "0.91.0",
      "published_at": "2022-04-03T06:38:21Z",
      "xpi_asset_id": 61404046,
      "xpi_name": "zotero-updateifs.xpi",
      "xpi_download_url": "https://github.com/redleafnew/zotero-updateifs/releases/download/0.91.0/zotero-updateifs.xpi",
      "addon_id": "zoteroupdateifs@redleafnew.me",
      "addon_name": "Zotero Update IFs",
      "addon_version": "0.91.0",
      "addon_description": "Zotero plugin for update IF from http://sci.justscience.cn/",
      "min_zotero_version": "3.0b1",
      "max_zotero_version": "6.*",
      "parse_success": true
    },
    {
      "tag": "0.8.0",
      "published_at": "2022-03-27T09:25:00Z",
      "xpi_asset_id": 60737888,
      "xpi_name": "zotero-updateifs.xpi",
      "xpi_download_url": "https://github.com/redleafnew/zotero-updateifs/releases/download/0.8.0/zotero-updateifs.xpi",
      "addon_id": "zoteroupdateifs@redleafnew.me",
      "addon_name": "Zotero Update IFs",
      "addon_version": "0.8.0",
      "addon_description": "Zotero plugin for update IF from http://sci.justscience.cn/",
      "min_zotero_version": "3.0b1",
      "max_zotero_version": "6.*",
      "parse_success": true
    },
    {
      "tag": "0.7.1",
      "published_at": "2022-03-22T01:59:20Z",
      "xpi_asset_id": 60193490,
      "xpi_name": "zotero-updateifs.xpi",
      "xpi_download_url": "https://github.com/redleafnew/zotero-updateifs/releases/download/0.7.1/zotero-updateifs.xpi",
      "addon_id": "zoteroupdateifs@redleafnew.me",
      "addon_name": "Zotero Update IFs",
      "addon_version": "0.7.1",
      "addon_description": "Zotero plugin for update IF from http://sci.justscience.cn/",
      "min_zotero_version": "3.0b1",
      "max_zotero_version": "6.*",
      "parse_success": true
    },
    {
      "tag": "0.7.0",
      "published_at": "2022-03-19T08:40:53Z",
      "xpi_asset_id": 59946169,
      "xpi_name": "zotero-updateifs.xpi",
      "xpi_download_url": "https://github.com/redleafnew/zotero-updateifs/releases/download/0.7.0/zotero-updateifs.xpi",
      "addon_id": "zoteroupdateifs@redleafnew.me",
      "addon_name": "Zotero Update IFs",
      "addon_version": "0.7.0",
      "addon_description": "Zotero plugin for update IF from http://sci.justscience.cn/",
      "min_zotero_version": "3.0b1",
      "max_zotero_version": "6.*",
      "parse_success": true
    },
    {
      "tag": "0.6.1",
      "published_at": "2022-03-14T13:25:29Z",
      "xpi_asset_id": 59458046,
      "xpi_name": "zotero-updateifs.xpi",
      "xpi_download_url": "https://github.com/redleafnew/zotero-updateifs/releases/download/0.6.1/zotero-updateifs.xpi",
      "addon_id": "zoteroupdateifs@redleafnew.me",
      "addon_name": "Zotero Update IFs",
      "addon_version": "0.6.1",
      "addon_description": "Zotero plugin for update IF from http://sci.justscience.cn/",
      "min_zotero_version": "3.0b1",
      "max_zotero_version": "6.*",
      "parse_success": true
    },
    {
      "tag": "0.6.0",
      "published_at": "2022-03-13T02:49:36Z",
      "xpi_asset_id": 59352889,
      "xpi_name": "zotero-updateifs.xpi",
      "xpi_download_url": "https://github.com/redleafnew/zotero-updateifs/releases/download/0.6.0/zotero-updateifs.xpi",
      "addon_id": "zoteroupdateifs@redleafnew.me",
      "addon_name": "Zotero Update IFs",
      "addon_version": "0.6.0",
      "addon_description": "Zotero plugin for update IF from http://sci.justscience.cn/",
      "min_zotero_version": "3.0b1",
      "max_zotero_version": "6.*",
      "parse_success": true
    },
    {
      "tag": "0.5.2",
      "published_at": "2022-03-11T09:16:18Z",
      "xpi_asset_id": 59201816,
      "xpi_name": "zotero-updateifs.xpi",
      "xpi_download_url": "https://github.com/redleafnew/zotero-updateifs/releases/download/0.5.2/zotero-updateifs.xpi",
      "addon_id": "zoteroupdateifs@redleafnew.me",
      "addon_name": "Zotero Update IFs",
      "addon_version": "0.5.2",
      "addon_description": "Zotero plugin for update IF from http://sci.justscience.cn/",
      "min_zotero_version": "3.0b1",
      "max_zotero_version": "6.*",
      "parse_success": true
    },
    {
      "tag": "0.5.1",
      "published_at": "2022-03-08T07:54:06Z",
      "xpi_asset_id": 58874361,
      "xpi_name": "zotero-updateifs.xpi",
      "xpi_download_url": "https://github.com/redleafnew/zotero-updateifs/releases/download/0.5.1/zotero-updateifs.xpi",
      "addon_id": "zoteroupdateifs@redleafnew.me",
      "addon_name": "Zotero Update IFs",
      "addon_version": "0.5.1",
      "addon_description": "Zotero plugin for update IF from http://sci.justscience.cn/",
      "min_zotero_version": "3.0b1",
      "max_zotero_version": "6.*",
      "parse_success": true
    },
    {
      "tag": "0.3.0",
      "published_at": "2022-03-04T01:34:53Z",
      "xpi_asset_id": 58501404,
      "xpi_name": "zotero-updateifs.xpi",
      "xpi_download_url": "https://github.com/redleafnew/zotero-updateifs/releases/download/0.3.0/zotero-updateifs.xpi",
      "addon_id": "zoteroupdateifs@redleafnew.me",
      "addon_name": "Zotero Update IFs",
      "addon_version": "0.3.0",
      "addon_description": "Zotero plugin for update IF from http://sci.justscience.cn/",
      "min_zotero_version": "3.0b1",
      "max_zotero_version": "6.*",
      "parse_success": true
    },
    {
      "tag": "0.2.0",
      "published_at": "2022-02-27T12:02:46Z",
      "xpi_asset_id": 58054387,
      "xpi_name": "zotero-updateifs.xpi",
      "xpi_download_url": "https://github.com/redleafnew/zotero-updateifs/releases/download/0.2.0/zotero-updateifs.xpi",
      "addon_id": "zoteroupdateifs@redleafnew.me",
      "addon_name": "Zotero Update IFs",
      "addon_version": "0.2.0",
      "addon_description": "Zotero plugin for update IF from http://sci.justscience.cn/",
      "min_zotero_version": "3.0b1",
      "max_zotero_version": "6.*",
      "parse_success": true
    },
    {
      "tag": "0.1.0",
      "published_at": "2022-02-23T09:59:47Z",
      "xpi_asset_id": 57682371,
      "xpi_name": "zotero-updateifs.xpi",
      "xpi_download_url": "https://github.com/redleafnew/zotero-updateifs/releases/download/0.1.0/zotero-updateifs.xpi",
      "addon_id": "zoteroupdateifs@redleafnew.me",
      "addon_name": "Zotero Update IFs",
      "addon_version": "0.1.0",
      "addon_description": "Zotero plugin for update IF from http://sci.justscience.cn/",
      "min_zotero_version": "3.0b1",
      "max_zotero_version": "6.*",
      "parse_success": true
    },
    {
      "tag": "0.0.10",
      "published_at": "2022-02-23T02:42:05Z",
      "xpi_asset_id": 57654195,
      "xpi_name": "zotero-updateifs.xpi",
      "xpi_download_url": "https://github.com/redleafnew/zotero-updateifs/releases/download/0.0.10/zotero-updateifs.xpi",
      "addon_id": "zoteroupdateifs@redleafnew.me",
      "addon_name": "Zotero Update IFs",
      "addon_version": "0.0.10",
      "addon_description": "Zotero plugin for update IF from http://sci.justscience.cn/",
      "min_zotero_version": "3.0b1",
      "max_zotero_version": "6.*",
      "parse_success": true
    },
    {
      "tag": "0.0.9",
      "published_at": "2022-02-23T00:01:05Z",
      "xpi_asset_id": 57644503,
      "xpi_name": "zotero-updateifs.xpi",
      "xpi_download_url": "https://github.com/redleafnew/zotero-updateifs/releases/download/0.0.9/zotero-updateifs.xpi",
      "addon_id": "zoteroupdateifs@redleafnew.me",
      "addon_name": "Zotero Update IFs",
      "addon_version": "0.0.9",
      "addon_description": "Zotero plugin for update IF from http://sci.justscience.cn/",
      "min_zotero_version": "3.0b1",
      "max_zotero_version": "6.*",
      "parse_success": true
    },
    {
      "tag": "0.0.8",
      "published_at": "2022-02-22T00:40:23Z",
      "xpi_asset_id": 57540154,
      "xpi_name": "zotero-updateifs.xpi",
      "xpi_download_url": "https://github.com/redleafnew/zotero-updateifs/releases/download/0.0.8/zotero-updateifs.xpi",
      "addon_id": "zoteroupdateifs@redleafnew.me",
      "addon_name": "Zotero Update IFs",
      "addon_version": "0.0.8",
      "addon_description": "Zotero plugin for update IF from http://sci.justscience.cn/",
      "min_zotero_version": "3.0b1",
      "max_zotero_version": "6.*",
      "parse_success": true
    },
    {
      "tag": "0.0.7",
      "published_at": "2022-02-05T02:24:10Z",
      "xpi_asset_id": 56497472,
      "xpi_name": "zotero-updateifs.xpi",
      "xpi_download_url": "https://github.com/redleafnew/zotero-updateifs/releases/download/0.0.7/zotero-updateifs.xpi",
      "addon_id": "zoteroupdateifs@redleafnew.me",
      "addon_name": "Zotero Update IFs",
      "addon_version": "0.0.7",
      "addon_description": "Zotero plugin for update IF from http://sci.justscience.cn/",
      "min_zotero_version": "3.0b1",
      "max_zotero_version": "6.*",
      "parse_success": true
    },
    {
      "tag": "0.0.6",
      "published_at": "2022-02-04T14:18:24Z",
      "xpi_asset_id": 55847714,
      "xpi_name": "zotero-updateifs.xpi",
      "xpi_download_url": "https://github.com/redleafnew/zotero-updateifs/releases/download/0.0.6/zotero-updateifs.xpi",
      "addon_id": "zoteroupdateifs@redleafnew.me",
      "addon_name": "Zotero Update IFs",
      "addon_version": "0.0.6",
      "addon_description": "Zotero plugin for update IF from http://sci.justscience.cn/",
      "min_zotero_version": "3.0b1",
      "max_zotero_version": "5.0.*",
      "parse_success": true
    },
    {
      "tag": "0.0.5",
      "published_at": "2022-02-04T07:11:07Z",
      "xpi_asset_id": 55831056,
      "xpi_name": "zotero-updateifs.xpi",
      "xpi_download_url": "https://github.com/redleafnew/zotero-updateifs/releases/download/0.0.5/zotero-updateifs.xpi",
      "addon_id": "zoteroupdateifs@redleafnew.me",
      "addon_name": "Zotero Update IFs",
      "addon_version": "0.0.5",
      "addon_description": "Zotero plugin for update IF from http://sci.justscience.cn/",
      "min_zotero_version": "3.0b1",
      "max_zotero_version": "5.0.*",
      "parse_success": true
    },
    {
      "tag": "0.0.4",
      "published_at": "2022-01-23T06:36:27Z",
      "xpi_asset_id": 54727446,
      "xpi_name": "zotero-updateifs.xpi",
      "xpi_download_url": "https://github.com/redleafnew/zotero-updateifs/releases/download/0.0.4/zotero-updateifs.xpi",
      "addon_id": "zoteroupdateifs@redleafnew.me",
      "addon_name": "Zotero Update IFs",
      "addon_version": "0.0.4",
      "addon_description": "Zotero plugin for update IF from http://sci.justscience.cn/",
      "min_zotero_version": "3.0b1",
      "max_zotero_version": "5.0.*",
      "parse_success": true
    },
    {
      "tag": "0.0.3",
      "published_at": "2022-01-21T09:42:24Z",
      "xpi_asset_id": 54726353,
      "xpi_name": "zotero-updateifs.xpi",
      "xpi_download_url": "https://github.com/redleafnew/zotero-updateifs/releases/download/0.0.3/zotero-updateifs.xpi",
      "addon_id": "zoteroupdateifs@redleafnew.me",
      "addon_name": "Zotero Update IFs",
      "addon_version": "0.0.3",
      "addon_description": "Zotero plugin for update IF from http://sci.justscience.cn/",
      "min_zotero_version": "3.0b1",
      "max_zotero_version": "5.0.*",
      "parse_success": true
    },
    {
      "tag": "0.0.2",
      "published_at": "2022-01-21T01:07:24Z",
      "xpi_asset_id": 54726250,
      "xpi_name": "zotero-updateifs.xpi",
      "xpi_download_url": "https://github.com/redleafnew/zotero-updateifs/releases/download/0.0.2/zotero-updateifs.xpi",
      "addon_id": "zoteroupdateifs@redleafnew.me",
      "addon_name": "Zotero Update IFs",
      "addon_version": "0.0.2",
      "addon_description": "Zotero plugin for update IF from http://sci.justscience.cn/",
      "min_zotero_version": "3.0b1",
      "max_zotero_version": "5.0.*",
      "parse_success": true
    },
    {
      "tag": "0.0.1",
      "published_at": "2022-01-20T02:02:42Z",
      "xpi_asset_id": 54725134,
      "xpi_name": "zotero-updateifs.xpi",
      "xpi_download_url": "https://github.com/redleafnew/zotero-updateifs/releases/download/0.0.1/zotero-updateifs.xpi",
      "addon_id": "zoteroupdateifs@redleafnew.me",
      "addon_name": "Zotero Update IFs",
      "addon_version": "0.0.1",
      "addon_description": "Zotero plugin for update IF from http://sci.justscience.cn/",
      "min_zotero_version": "3.0b1",
      "max_zotero_version": "5.0.*",
      "parse_success": true
    }
  ]
}