{
  "last_checked": "2026-01-28T07:22:46.704990+00:00",
  "checked_releases": [
    {
      "tag": "1.2.26",
      "published_at": "2025-12-12T08:35:00Z",
      "xpi_asset_id": 327767891,
      "xpi_name": "zotmoov-1.2.26-fx.xpi",
      "xpi_download_url": "https://github.com/wileyyugioh/zotmoov/releases/download/1.2.26/zotmoov-1.2.26-fx.xpi",
      "addon_id": "zotmoov@wileyy.com",
      "addon_name": "ZotMoov",
      "addon_version": "1.2.26",
      "addon_description": "Mooves attachments and links them",
      "min_zotero_version": "6.999",
      "max_zotero_version": "8.0.*",
      "update_url": "https://raw.githubusercontent.com/wileyyugioh/zotmoov/master/updates.json",
      "parse_success": true
    },
    {
      "tag": "1.2.25",
      "published_at": "2025-10-22T01:45:16Z",
      "xpi_asset_id": 307131714,
      "xpi_name": "zotmoov-1.2.25-fx.xpi",
      "xpi_download_url": "https://github.com/wileyyugioh/zotmoov/releases/download/1.2.25/zotmoov-1.2.25-fx.xpi",
      "addon_id": "zotmoov@wileyy.com",
      "addon_name": "ZotMoov",
      "addon_version": "1.2.25",
      "addon_description": "Mooves attachments and links them",
      "min_zotero_version": "6.999",
      "max_zotero_version": "8.0.*",
      "update_url": "https://raw.githubusercontent.com/wileyyugioh/zotmoov/master/updates.json",
      "parse_success": true
    },
    {
      "tag": "1.2.24",
      "published_at": "2025-09-03T00:52:32Z",
      "xpi_asset_id": 289010273,
      "xpi_name": "zotmoov-1.2.24-fx.xpi",
      "xpi_download_url": "https://github.com/wileyyugioh/zotmoov/releases/download/1.2.25/zotmoov-1.2.25-fx.xpi",
      "addon_id": "zotmoov@wileyy.com",
      "addon_name": "ZotMoov",
      "addon_version": "1.2.25",
      "addon_description": "Mooves attachments and links them",
      "min_zotero_version": "6.999",
      "max_zotero_version": "8.0.*",
      "update_url": "https://raw.githubusercontent.com/wileyyugioh/zotmoov/master/updates.json",
      "parse_success": true
    },
    {
      "tag": "1.2.23",
      "published_at": "2025-08-22T04:54:27Z",
      "xpi_asset_id": 285036277,
      "xpi_name": "zotmoov-1.2.23-fx.xpi",
      "xpi_download_url": "https://github.com/wileyyugioh/zotmoov/releases/download/1.2.25/zotmoov-1.2.25-fx.xpi",
      "addon_id": "zotmoov@wileyy.com",
      "addon_name": "ZotMoov",
      "addon_version": "1.2.25",
      "addon_description": "Mooves attachments and links them",
      "min_zotero_version": "6.999",
      "max_zotero_version": "8.0.*",
      "update_url": "https://raw.githubusercontent.com/wileyyugioh/zotmoov/master/updates.json",
      "parse_success": true
    },
    {
      "tag": "1.2.22",
      "published_at": "2025-08-10T04:37:26Z",
      "xpi_asset_id": 281076025,
      "xpi_name": "zotmoov-1.2.22-fx.xpi",
      "xpi_download_url": "https://github.com/wileyyugioh/zotmoov/releases/download/1.2.25/zotmoov-1.2.25-fx.xpi",
      "addon_id": "zotmoov@wileyy.com",
      "addon_name": "ZotMoov",
      "addon_version": "1.2.25",
      "addon_description": "Mooves attachments and links them",
      "min_zotero_version": "6.999",
      "max_zotero_version": "8.0.*",
      "update_url": "https://raw.githubusercontent.com/wileyyugioh/zotmoov/master/updates.json",
      "parse_success": true
    },
    {
      "tag": "1.2.21",
      "published_at": "2025-04-16T06:01:24Z",
      "xpi_asset_id": 246820346,
      "xpi_name": "zotmoov-1.2.21-fx.xpi",
      "xpi_download_url": "https://github.com/wileyyugioh/zotmoov/releases/download/1.2.25/zotmoov-1.2.25-fx.xpi",
      "addon_id": "zotmoov@wileyy.com",
      "addon_name": "ZotMoov",
      "addon_version": "1.2.25",
      "addon_description": "Mooves attachments and links them",
      "min_zotero_version": "6.999",
      "max_zotero_version": "8.0.*",
      "update_url": "https://raw.githubusercontent.com/wileyyugioh/zotmoov/master/updates.json",
      "parse_success": true
    },
    {
      "tag": "1.2.20",
      "published_at": "2025-04-08T07:00:38Z",
      "xpi_asset_id": 244481302,
      "xpi_name": "zotmoov-1.2.20-fx.xpi",
      "xpi_download_url": "https://github.com/wileyyugioh/zotmoov/releases/download/1.2.25/zotmoov-1.2.25-fx.xpi",
      "addon_id": "zotmoov@wileyy.com",
      "addon_name": "ZotMoov",
      "addon_version": "1.2.25",
      "addon_description": "Mooves attachments and links them",
      "min_zotero_version": "6.999",
      "max_zotero_version": "8.0.*",
      "update_url": "https://raw.githubusercontent.com/wileyyugioh/zotmoov/master/updates.json",
      "parse_success": true
    },
    {
      "tag": "1.2.19",
      "published_at": "2025-03-16T06:13:40Z",
      "xpi_asset_id": 237896258,
      "xpi_name": "zotmoov-1.2.19-fx.xpi",
      "xpi_download_url": "https://github.com/wileyyugioh/zotmoov/releases/download/1.2.25/zotmoov-1.2.25-fx.xpi",
      "addon_id": "zotmoov@wileyy.com",
      "addon_name": "ZotMoov",
      "addon_version": "1.2.25",
      "addon_description": "Mooves attachments and links them",
      "min_zotero_version": "6.999",
      "max_zotero_version": "8.0.*",
      "update_url": "https://raw.githubusercontent.com/wileyyugioh/zotmoov/master/updates.json",
      "parse_success": true
    },
    {
      "tag": "1.2.18",
      "published_at": "2025-03-09T05:08:18Z",
      "xpi_asset_id": 235867023,
      "xpi_name": "zotmoov-1.2.18-fx.xpi",
      "xpi_download_url": "https://github.com/wileyyugioh/zotmoov/releases/download/1.2.25/zotmoov-1.2.25-fx.xpi",
      "addon_id": "zotmoov@wileyy.com",
      "addon_name": "ZotMoov",
      "addon_version": "1.2.25",
      "addon_description": "Mooves attachments and links them",
      "min_zotero_version": "6.999",
      "max_zotero_version": "8.0.*",
      "update_url": "https://raw.githubusercontent.com/wileyyugioh/zotmoov/master/updates.json",
      "parse_success": true
    },
    {
      "tag": "1.2.17",
      "published_at": "2025-02-26T07:47:49Z",
      "xpi_asset_id": 232679921,
      "xpi_name": "zotmoov-1.2.17-fx.xpi",
      "xpi_download_url": "https://github.com/wileyyugioh/zotmoov/releases/download/1.2.25/zotmoov-1.2.25-fx.xpi",
      "addon_id": "zotmoov@wileyy.com",
      "addon_name": "ZotMoov",
      "addon_version": "1.2.25",
      "addon_description": "Mooves attachments and links them",
      "min_zotero_version": "6.999",
      "max_zotero_version": "8.0.*",
      "update_url": "https://raw.githubusercontent.com/wileyyugioh/zotmoov/master/updates.json",
      "parse_success": true
    },
    {
      "tag": "1.2.16",
      "published_at": "2025-02-25T07:35:27Z",
      "xpi_asset_id": 232346071,
      "xpi_name": "zotmoov-1.2.16-fx.xpi",
      "xpi_download_url": "https://github.com/wileyyugioh/zotmoov/releases/download/1.2.25/zotmoov-1.2.25-fx.xpi",
      "addon_id": "zotmoov@wileyy.com",
      "addon_name": "ZotMoov",
      "addon_version": "1.2.25",
      "addon_description": "Mooves attachments and links them",
      "min_zotero_version": "6.999",
      "max_zotero_version": "8.0.*",
      "update_url": "https://raw.githubusercontent.com/wileyyugioh/zotmoov/master/updates.json",
      "parse_success": true
    },
    {
      "tag": "1.2.15",
      "published_at": "2025-01-24T09:05:12Z",
      "xpi_asset_id": 223051608,
      "xpi_name": "zotmoov-1.2.15-fx.xpi",
      "xpi_download_url": "https://github.com/wileyyugioh/zotmoov/releases/download/1.2.25/zotmoov-1.2.25-fx.xpi",
      "addon_id": "zotmoov@wileyy.com",
      "addon_name": "ZotMoov",
      "addon_version": "1.2.25",
      "addon_description": "Mooves attachments and links them",
      "min_zotero_version": "6.999",
      "max_zotero_version": "8.0.*",
      "update_url": "https://raw.githubusercontent.com/wileyyugioh/zotmoov/master/updates.json",
      "parse_success": true
    },
    {
      "tag": "1.2.14",
      "published_at": "2025-01-24T03:07:01Z",
      "xpi_asset_id": 222985640,
      "xpi_name": "zotmoov-1.2.14-fx.xpi",
      "xpi_download_url": "https://github.com/wileyyugioh/zotmoov/releases/download/1.2.25/zotmoov-1.2.25-fx.xpi",
      "addon_id": "zotmoov@wileyy.com",
      "addon_name": "ZotMoov",
      "addon_version": "1.2.25",
      "addon_description": "Mooves attachments and links them",
      "min_zotero_version": "6.999",
      "max_zotero_version": "8.0.*",
      "update_url": "https://raw.githubusercontent.com/wileyyugioh/zotmoov/master/updates.json",
      "parse_success": true
    },
    {
      "tag": "1.2.13",
      "published_at": "2025-01-22T02:27:35Z",
      "xpi_asset_id": 222288907,
      "xpi_name": "zotmoov-1.2.13-fx.xpi",
      "xpi_download_url": "https://github.com/wileyyugioh/zotmoov/releases/download/1.2.25/zotmoov-1.2.25-fx.xpi",
      "addon_id": "zotmoov@wileyy.com",
      "addon_name": "ZotMoov",
      "addon_version": "1.2.25",
      "addon_description": "Mooves attachments and links them",
      "min_zotero_version": "6.999",
      "max_zotero_version": "8.0.*",
      "update_url": "https://raw.githubusercontent.com/wileyyugioh/zotmoov/master/updates.json",
      "parse_success": true
    },
    {
      "tag": "1.2.12",
      "published_at": "2025-01-22T01:15:13Z",
      "xpi_asset_id": 222269081,
      "xpi_name": "zotmoov-1.2.12-fx.xpi",
      "xpi_download_url": "https://github.com/wileyyugioh/zotmoov/releases/download/1.2.25/zotmoov-1.2.25-fx.xpi",
      "addon_id": "zotmoov@wileyy.com",
      "addon_name": "ZotMoov",
      "addon_version": "1.2.25",
      "addon_description": "Mooves attachments and links them",
      "min_zotero_version": "6.999",
      "max_zotero_version": "8.0.*",
      "update_url": "https://raw.githubusercontent.com/wileyyugioh/zotmoov/master/updates.json",
      "parse_success": true
    },
    {
      "tag": "1.2.11",
      "published_at": "2024-12-30T04:09:07Z",
      "xpi_asset_id": 220534413,
      "xpi_name": "zotmoov-1.2.11-fx.xpi",
      "xpi_download_url": "https://github.com/wileyyugioh/zotmoov/releases/download/1.2.25/zotmoov-1.2.25-fx.xpi",
      "addon_id": "zotmoov@wileyy.com",
      "addon_name": "ZotMoov",
      "addon_version": "1.2.25",
      "addon_description": "Mooves attachments and links them",
      "min_zotero_version": "6.999",
      "max_zotero_version": "8.0.*",
      "update_url": "https://raw.githubusercontent.com/wileyyugioh/zotmoov/master/updates.json",
      "parse_success": true
    },
    {
      "tag": "1.2.10",
      "published_at": "2024-12-20T00:04:34Z",
      "xpi_asset_id": 214580082,
      "xpi_name": "zotmoov-1.2.10-fx.xpi",
      "xpi_download_url": "https://github.com/wileyyugioh/zotmoov/releases/download/1.2.25/zotmoov-1.2.25-fx.xpi",
      "addon_id": "zotmoov@wileyy.com",
      "addon_name": "ZotMoov",
      "addon_version": "1.2.25",
      "addon_description": "Mooves attachments and links them",
      "min_zotero_version": "6.999",
      "max_zotero_version": "8.0.*",
      "update_url": "https://raw.githubusercontent.com/wileyyugioh/zotmoov/master/updates.json",
      "parse_success": true
    },
    {
      "tag": "1.2.9",
      "published_at": "2024-12-07T09:29:16Z",
      "xpi_asset_id": 211731177,
      "xpi_name": "zotmoov-1.2.9-fx.xpi",
      "xpi_download_url": "https://github.com/wileyyugioh/zotmoov/releases/download/1.2.25/zotmoov-1.2.25-fx.xpi",
      "addon_id": "zotmoov@wileyy.com",
      "addon_name": "ZotMoov",
      "addon_version": "1.2.25",
      "addon_description": "Mooves attachments and links them",
      "min_zotero_version": "6.999",
      "max_zotero_version": "8.0.*",
      "update_url": "https://raw.githubusercontent.com/wileyyugioh/zotmoov/master/updates.json",
      "parse_success": true
    },
    {
      "tag": "1.2.8",
      "published_at": "2024-12-01T22:41:28Z",
      "xpi_asset_id": 210325558,
      "xpi_name": "zotmoov-1.2.8-fx.xpi",
      "xpi_download_url": "https://github.com/wileyyugioh/zotmoov/releases/download/1.2.25/zotmoov-1.2.25-fx.xpi",
      "addon_id": "zotmoov@wileyy.com",
      "addon_name": "ZotMoov",
      "addon_version": "1.2.25",
      "addon_description": "Mooves attachments and links them",
      "min_zotero_version": "6.999",
      "max_zotero_version": "8.0.*",
      "update_url": "https://raw.githubusercontent.com/wileyyugioh/zotmoov/master/updates.json",
      "parse_success": true
    },
    {
      "tag": "1.2.7",
      "published_at": "2024-11-27T18:06:50Z",
      "xpi_asset_id": 209466867,
      "xpi_name": "zotmoov-1.2.7-fx.xpi",
      "xpi_download_url": "https://github.com/wileyyugioh/zotmoov/releases/download/1.2.25/zotmoov-1.2.25-fx.xpi",
      "addon_id": "zotmoov@wileyy.com",
      "addon_name": "ZotMoov",
      "addon_version": "1.2.25",
      "addon_description": "Mooves attachments and links them",
      "min_zotero_version": "6.999",
      "max_zotero_version": "8.0.*",
      "update_url": "https://raw.githubusercontent.com/wileyyugioh/zotmoov/master/updates.json",
      "parse_success": true
    },
    {
      "tag": "1.2.6",
      "published_at": "2024-11-27T02:32:06Z",
      "xpi_asset_id": 209320821,
      "xpi_name": "zotmoov-1.2.6-fx.xpi",
      "xpi_download_url": "https://github.com/wileyyugioh/zotmoov/releases/download/1.2.25/zotmoov-1.2.25-fx.xpi",
      "addon_id": "zotmoov@wileyy.com",
      "addon_name": "ZotMoov",
      "addon_version": "1.2.25",
      "addon_description": "Mooves attachments and links them",
      "min_zotero_version": "6.999",
      "max_zotero_version": "8.0.*",
      "update_url": "https://raw.githubusercontent.com/wileyyugioh/zotmoov/master/updates.json",
      "parse_success": true
    },
    {
      "tag": "1.2.5",
      "published_at": "2024-11-18T07:10:21Z",
      "xpi_asset_id": 207268178,
      "xpi_name": "zotmoov-1.2.5-fx.xpi",
      "xpi_download_url": "https://github.com/wileyyugioh/zotmoov/releases/download/1.2.25/zotmoov-1.2.25-fx.xpi",
      "addon_id": "zotmoov@wileyy.com",
      "addon_name": "ZotMoov",
      "addon_version": "1.2.25",
      "addon_description": "Mooves attachments and links them",
      "min_zotero_version": "6.999",
      "max_zotero_version": "8.0.*",
      "update_url": "https://raw.githubusercontent.com/wileyyugioh/zotmoov/master/updates.json",
      "parse_success": true
    },
    {
      "tag": "1.2.4",
      "published_at": "2024-11-15T17:49:48Z",
      "xpi_asset_id": 206785984,
      "xpi_name": "zotmoov-1.2.4-fx.xpi",
      "xpi_download_url": "https://github.com/wileyyugioh/zotmoov/releases/download/1.2.25/zotmoov-1.2.25-fx.xpi",
      "addon_id": "zotmoov@wileyy.com",
      "addon_name": "ZotMoov",
      "addon_version": "1.2.25",
      "addon_description": "Mooves attachments and links them",
      "min_zotero_version": "6.999",
      "max_zotero_version": "8.0.*",
      "update_url": "https://raw.githubusercontent.com/wileyyugioh/zotmoov/master/updates.json",
      "parse_success": true
    },
    {
      "tag": "1.2.3",
      "published_at": "2024-11-15T02:39:28Z",
      "xpi_asset_id": 206632681,
      "xpi_name": "zotmoov-1.2.3-fx.xpi",
      "xpi_download_url": "https://github.com/wileyyugioh/zotmoov/releases/download/1.2.25/zotmoov-1.2.25-fx.xpi",
      "addon_id": "zotmoov@wileyy.com",
      "addon_name": "ZotMoov",
      "addon_version": "1.2.25",
      "addon_description": "Mooves attachments and links them",
      "min_zotero_version": "6.999",
      "max_zotero_version": "8.0.*",
      "update_url": "https://raw.githubusercontent.com/wileyyugioh/zotmoov/master/updates.json",
      "parse_success": true
    },
    {
      "tag": "1.2.2",
      "published_at": "2024-11-14T01:41:15Z",
      "xpi_asset_id": 206354973,
      "xpi_name": "zotmoov-1.2.2-fx.xpi",
      "xpi_download_url": "https://github.com/wileyyugioh/zotmoov/releases/download/1.2.25/zotmoov-1.2.25-fx.xpi",
      "addon_id": "zotmoov@wileyy.com",
      "addon_name": "ZotMoov",
      "addon_version": "1.2.25",
      "addon_description": "Mooves attachments and links them",
      "min_zotero_version": "6.999",
      "max_zotero_version": "8.0.*",
      "update_url": "https://raw.githubusercontent.com/wileyyugioh/zotmoov/master/updates.json",
      "parse_success": true
    },
    {
      "tag": "1.2.1",
      "published_at": "2024-11-13T07:10:31Z",
      "xpi_asset_id": 206142913,
      "xpi_name": "zotmoov-1.2.1-fx.xpi",
      "xpi_download_url": "https://github.com/wileyyugioh/zotmoov/releases/download/1.2.25/zotmoov-1.2.25-fx.xpi",
      "addon_id": "zotmoov@wileyy.com",
      "addon_name": "ZotMoov",
      "addon_version": "1.2.25",
      "addon_description": "Mooves attachments and links them",
      "min_zotero_version": "6.999",
      "max_zotero_version": "8.0.*",
      "update_url": "https://raw.githubusercontent.com/wileyyugioh/zotmoov/master/updates.json",
      "parse_success": true
    },
    {
      "tag": "1.2.0",
      "published_at": "2024-11-13T06:32:56Z",
      "xpi_asset_id": 206138076,
      "xpi_name": "zotmoov-1.2.0-fx.xpi",
      "xpi_download_url": "https://github.com/wileyyugioh/zotmoov/releases/download/1.2.25/zotmoov-1.2.25-fx.xpi",
      "addon_id": "zotmoov@wileyy.com",
      "addon_name": "ZotMoov",
      "addon_version": "1.2.25",
      "addon_description": "Mooves attachments and links them",
      "min_zotero_version": "6.999",
      "max_zotero_version": "8.0.*",
      "update_url": "https://raw.githubusercontent.com/wileyyugioh/zotmoov/master/updates.json",
      "parse_success": true
    },
    {
      "tag": "1.1.15",
      "published_at": "2024-09-28T17:37:53Z",
      "xpi_asset_id": 195548577,
      "xpi_name": "zotmoov-1.1.15-fx.xpi",
      "xpi_download_url": "https://github.com/wileyyugioh/zotmoov/releases/download/1.2.25/zotmoov-1.2.25-fx.xpi",
      "addon_id": "zotmoov@wileyy.com",
      "addon_name": "ZotMoov",
      "addon_version": "1.2.25",
      "addon_description": "Mooves attachments and links them",
      "min_zotero_version": "6.999",
      "max_zotero_version": "8.0.*",
      "update_url": "https://raw.githubusercontent.com/wileyyugioh/zotmoov/master/updates.json",
      "parse_success": true
    },
    {
      "tag": "1.1.14",
      "published_at": "2024-09-13T02:28:16Z",
      "xpi_asset_id": 192343395,
      "xpi_name": "zotmoov-1.1.14-fx.xpi",
      "xpi_download_url": "https://github.com/wileyyugioh/zotmoov/releases/download/1.2.25/zotmoov-1.2.25-fx.xpi",
      "addon_id": "zotmoov@wileyy.com",
      "addon_name": "ZotMoov",
      "addon_version": "1.2.25",
      "addon_description": "Mooves attachments and links them",
      "min_zotero_version": "6.999",
      "max_zotero_version": "8.0.*",
      "update_url": "https://raw.githubusercontent.com/wileyyugioh/zotmoov/master/updates.json",
      "parse_success": true
    },
    {
      "tag": "1.1.13",
      "published_at": "2024-08-30T08:41:05Z",
      "xpi_asset_id": 189316377,
      "xpi_name": "zotmoov-1.1.13-fx.xpi",
      "xpi_download_url": "https://github.com/wileyyugioh/zotmoov/releases/download/1.2.25/zotmoov-1.2.25-fx.xpi",
      "addon_id": "zotmoov@wileyy.com",
      "addon_name": "ZotMoov",
      "addon_version": "1.2.25",
      "addon_description": "Mooves attachments and links them",
      "min_zotero_version": "6.999",
      "max_zotero_version": "8.0.*",
      "update_url": "https://raw.githubusercontent.com/wileyyugioh/zotmoov/master/updates.json",
      "parse_success": true
    },
    {
      "tag": "1.1.12",
      "published_at": "2024-08-28T02:23:47Z",
      "xpi_asset_id": 188756784,
      "xpi_name": "zotmoov-1.1.12-fx.xpi",
      "xpi_download_url": "https://github.com/wileyyugioh/zotmoov/releases/download/1.1.12/zotmoov-1.1.12-fx.xpi",
      "addon_id": "zotmoov@wileyy.com",
      "addon_name": "ZotMoov",
      "addon_version": "1.1.12",
      "addon_description": "Mooves attachments and links them",
      "min_zotero_version": "6.999",
      "max_zotero_version": "7.0.*",
      "update_url": "https://raw.githubusercontent.com/wileyyugioh/zotmoov/master/updates.json",
      "parse_success": true
    },
    {
      "tag": "1.1.11",
      "published_at": "2024-08-28T01:24:22Z",
      "xpi_asset_id": 188747419,
      "xpi_name": "zotmoov-1.1.11-fx.xpi",
      "xpi_download_url": "https://github.com/wileyyugioh/zotmoov/releases/download/1.1.11/zotmoov-1.1.11-fx.xpi",
      "addon_id": "zotmoov@wileyy.com",
      "addon_name": "ZotMoov",
      "addon_version": "1.1.11",
      "addon_description": "Mooves attachments and links them",
      "min_zotero_version": "6.999",
      "max_zotero_version": "7.0.*",
      "update_url": "https://raw.githubusercontent.com/wileyyugioh/zotmoov/master/updates.json",
      "parse_success": true
    },
    {
      "tag": "1.1.10",
      "published_at": "2024-08-28T01:07:03Z",
      "xpi_asset_id": 188743999,
      "xpi_name": "zotmoov-1.1.10-fx.xpi",
      "xpi_download_url": "https://github.com/wileyyugioh/zotmoov/releases/download/1.1.10/zotmoov-1.1.10-fx.xpi",
      "addon_id": "zotmoov@wileyy.com",
      "addon_name": "ZotMoov",
      "addon_version": "1.1.10",
      "addon_description": "Mooves attachments and links them",
      "min_zotero_version": "6.999",
      "max_zotero_version": "7.0.*",
      "update_url": "https://raw.githubusercontent.com/wileyyugioh/zotmoov/master/updates.json",
      "parse_success": true
    },
    {
      "tag": "1.1.9",
      "published_at": "2024-08-27T10:05:06Z",
      "xpi_asset_id": 188581261,
      "xpi_name": "zotmoov-1.1.9-fx.xpi",
      "xpi_download_url": "https://github.com/wileyyugioh/zotmoov/releases/download/1.1.9/zotmoov-1.1.9-fx.xpi",
      "addon_id": "zotmoov@wileyy.com",
      "addon_name": "ZotMoov",
      "addon_version": "1.1.9",
      "addon_description": "Mooves attachments and links them",
      "min_zotero_version": "6.999",
      "max_zotero_version": "7.0.*",
      "update_url": "https://raw.githubusercontent.com/wileyyugioh/zotmoov/master/updates.json",
      "parse_success": true
    },
    {
      "tag": "1.1.8",
      "published_at": "2024-08-18T21:47:27Z",
      "xpi_asset_id": 186761642,
      "xpi_name": "zotmoov-1.1.8-fx.xpi",
      "xpi_download_url": "https://github.com/wileyyugioh/zotmoov/releases/download/1.1.8/zotmoov-1.1.8-fx.xpi",
      "addon_id": "zotmoov@wileyy.com",
      "addon_name": "ZotMoov",
      "addon_version": "1.1.8",
      "addon_description": "Mooves attachments and links them",
      "min_zotero_version": "6.999",
      "max_zotero_version": "7.0.*",
      "update_url": "https://raw.githubusercontent.com/wileyyugioh/zotmoov/master/updates.json",
      "parse_success": true
    },
    {
      "tag": "1.1.7",
      "published_at": "2024-08-16T17:12:37Z",
      "xpi_asset_id": 186403082,
      "xpi_name": "zotmoov-1.1.7-fx.xpi",
      "xpi_download_url": "https://github.com/wileyyugioh/zotmoov/releases/download/1.1.7/zotmoov-1.1.7-fx.xpi",
      "addon_id": "zotmoov@wileyy.com",
      "addon_name": "ZotMoov",
      "addon_version": "1.1.7",
      "addon_description": "Mooves attachments and links them",
      "min_zotero_version": "6.999",
      "max_zotero_version": "7.0.*",
      "update_url": "https://raw.githubusercontent.com/wileyyugioh/zotmoov/master/updates.json",
      "parse_success": true
    },
    {
      "tag": "1.1.6",
      "published_at": "2024-08-16T05:57:04Z",
      "xpi_asset_id": 186307451,
      "xpi_name": "zotmoov-1.1.6-fx.xpi",
      "xpi_download_url": "https://github.com/wileyyugioh/zotmoov/releases/download/1.1.6/zotmoov-1.1.6-fx.xpi",
      "addon_id": "zotmoov@wileyy.com",
      "addon_name": "ZotMoov",
      "addon_version": "1.1.6",
      "addon_description": "Mooves attachments and links them",
      "min_zotero_version": "6.999",
      "max_zotero_version": "7.0.*",
      "update_url": "https://raw.githubusercontent.com/wileyyugioh/zotmoov/master/updates.json",
      "parse_success": true
    },
    {
      "tag": "1.1.5",
      "published_at": "2024-08-16T02:25:48Z",
      "xpi_asset_id": 186279675,
      "xpi_name": "zotmoov-1.1.5-fx.xpi",
      "xpi_download_url": "https://github.com/wileyyugioh/zotmoov/releases/download/1.1.5/zotmoov-1.1.5-fx.xpi",
      "addon_id": "zotmoov@wileyy.com",
      "addon_name": "ZotMoov",
      "addon_version": "1.1.5",
      "addon_description": "Mooves attachments and links them",
      "min_zotero_version": "6.999",
      "max_zotero_version": "7.0.*",
      "update_url": "https://raw.githubusercontent.com/wileyyugioh/zotmoov/master/updates.json",
      "parse_success": true
    },
    {
      "tag": "1.1.4",
      "published_at": "2024-08-16T02:04:21Z",
      "xpi_asset_id": 186277304,
      "xpi_name": "zotmoov-1.1.4-fx.xpi",
      "xpi_download_url": "https://github.com/wileyyugioh/zotmoov/releases/download/1.1.4/zotmoov-1.1.4-fx.xpi",
      "addon_id": "zotmoov@wileyy.com",
      "addon_name": "ZotMoov",
      "addon_version": "1.1.4",
      "addon_description": "Mooves attachments and links them",
      "min_zotero_version": "6.999",
      "max_zotero_version": "7.0.*",
      "update_url": "https://raw.githubusercontent.com/wileyyugioh/zotmoov/master/updates.json",
      "parse_success": true
    },
    {
      "tag": "1.1.3",
      "published_at": "2024-08-15T00:12:15Z",
      "xpi_asset_id": 186029213,
      "xpi_name": "zotmoov-1.1.3-fx.xpi",
      "xpi_download_url": "https://github.com/wileyyugioh/zotmoov/releases/download/1.1.3/zotmoov-1.1.3-fx.xpi",
      "addon_id": "zotmoov@wileyy.com",
      "addon_name": "ZotMoov",
      "addon_version": "1.1.3",
      "addon_description": "Mooves attachments and links them",
      "min_zotero_version": "6.999",
      "max_zotero_version": "7.0.*",
      "update_url": "https://raw.githubusercontent.com/wileyyugioh/zotmoov/master/updates.json",
      "parse_success": true
    },
    {
      "tag": "1.1.2",
      "published_at": "2024-08-14T01:49:53Z",
      "xpi_asset_id": 185824050,
      "xpi_name": "zotmoov-1.1.2-fx.xpi",
      "xpi_download_url": "https://github.com/wileyyugioh/zotmoov/releases/download/1.1.2/zotmoov-1.1.2-fx.xpi",
      "addon_id": "zotmoov@wileyy.com",
      "addon_name": "ZotMoov",
      "addon_version": "1.1.2",
      "addon_description": "Mooves attachments and links them",
      "min_zotero_version": "6.999",
      "max_zotero_version": "7.0.*",
      "update_url": "https://raw.githubusercontent.com/wileyyugioh/zotmoov/master/updates.json",
      "parse_success": true
    },
    {
      "tag": "1.1.1",
      "published_at": "2024-08-13T04:26:09Z",
      "xpi_asset_id": 185609509,
      "xpi_name": "zotmoov-1.1.1-fx.xpi",
      "xpi_download_url": "https://github.com/wileyyugioh/zotmoov/releases/download/1.1.1/zotmoov-1.1.1-fx.xpi",
      "addon_id": "zotmoov@wileyy.com",
      "addon_name": "ZotMoov",
      "addon_version": "1.1.1",
      "addon_description": "Mooves attachments and links them",
      "min_zotero_version": "6.999",
      "max_zotero_version": "7.0.*",
      "update_url": "https://raw.githubusercontent.com/wileyyugioh/zotmoov/master/updates.json",
      "parse_success": true
    },
    {
      "tag": "1.1.0",
      "published_at": "2024-08-13T04:08:47Z",
      "xpi_asset_id": 185607865,
      "xpi_name": "zotmoov-1.1.0-fx.xpi",
      "xpi_download_url": "https://github.com/wileyyugioh/zotmoov/releases/download/1.1.0/zotmoov-1.1.0-fx.xpi",
      "addon_id": "zotmoov@wileyy.com",
      "addon_name": "ZotMoov",
      "addon_version": "1.1.0",
      "addon_description": "Mooves attachments and links them",
      "min_zotero_version": "6.999",
      "max_zotero_version": "7.0.*",
      "update_url": "https://raw.githubusercontent.com/wileyyugioh/zotmoov/master/updates.json",
      "parse_success": true
    },
    {
      "tag": "1.0.0.10",
      "published_at": "2024-08-10T03:11:58Z",
      "xpi_asset_id": 185076520,
      "xpi_name": "zotmoov-1.0.0.10-fx.xpi",
      "xpi_download_url": "https://github.com/wileyyugioh/zotmoov/releases/download/1.0.0.10/zotmoov-1.0.0.10-fx.xpi",
      "addon_id": "zotmoov@wileyy.com",
      "addon_name": "ZotMoov",
      "addon_version": "1.0.0.10",
      "addon_description": "Mooves attachments and links them",
      "min_zotero_version": "6.999",
      "max_zotero_version": "7.0.*",
      "update_url": "https://raw.githubusercontent.com/wileyyugioh/zotmoov/master/updates.json",
      "parse_success": true
    },
    {
      "tag": "1.0.0.9",
      "published_at": "2024-08-08T12:38:08Z",
      "xpi_asset_id": 184685735,
      "xpi_name": "zotmoov-1.0.0.9-fx.xpi",
      "xpi_download_url": "https://github.com/wileyyugioh/zotmoov/releases/download/1.0.0.9/zotmoov-1.0.0.9-fx.xpi",
      "addon_id": "zotmoov@wileyy.com",
      "addon_name": "ZotMoov",
      "addon_version": "1.0.0.9",
      "addon_description": "Mooves attachments and links them",
      "min_zotero_version": "6.999",
      "max_zotero_version": "7.0.*",
      "update_url": "https://raw.githubusercontent.com/wileyyugioh/zotmoov/master/updates.json",
      "parse_success": true
    },
    {
      "tag": "1.0.0.8",
      "published_at": "2024-08-08T10:49:24Z",
      "xpi_asset_id": 184666734,
      "xpi_name": "zotmoov-1.0.0.8-fx.xpi",
      "xpi_download_url": "https://github.com/wileyyugioh/zotmoov/releases/download/1.0.0.8/zotmoov-1.0.0.8-fx.xpi",
      "addon_id": "zotmoov@wileyy.com",
      "addon_name": "ZotMoov",
      "addon_version": "1.0.0.8",
      "addon_description": "Mooves attachments and links them",
      "min_zotero_version": "6.999",
      "max_zotero_version": "7.0.*",
      "update_url": "https://raw.githubusercontent.com/wileyyugioh/zotmoov/master/updates.json",
      "parse_success": true
    },
    {
      "tag": "1.0.0.7",
      "published_at": "2024-08-07T05:39:16Z",
      "xpi_asset_id": 184383014,
      "xpi_name": "zotmoov-1.0.0.7-fx.xpi",
      "xpi_download_url": "https://github.com/wileyyugioh/zotmoov/releases/download/1.0.0.7/zotmoov-1.0.0.7-fx.xpi",
      "addon_id": "zotmoov@wileyy.com",
      "addon_name": "ZotMoov",
      "addon_version": "1.0.0.7",
      "addon_description": "Mooves attachments and links them",
      "min_zotero_version": "6.999",
      "max_zotero_version": "7.0.*",
      "update_url": "https://raw.githubusercontent.com/wileyyugioh/zotmoov/master/updates.json",
      "parse_success": true
    },
    {
      "tag": "1.0.0.6",
      "published_at": "2024-08-03T18:32:52Z",
      "xpi_asset_id": 183681372,
      "xpi_name": "zotmoov-1.0.0.6-fx.xpi",
      "xpi_download_url": "https://github.com/wileyyugioh/zotmoov/releases/download/1.0.0.6/zotmoov-1.0.0.6-fx.xpi",
      "addon_id": "zotmoov@wileyy.com",
      "addon_name": "ZotMoov",
      "addon_version": "1.0.0.6",
      "addon_description": "Mooves attachments and links them",
      "min_zotero_version": "6.999",
      "max_zotero_version": "7.0.*",
      "update_url": "https://raw.githubusercontent.com/wileyyugioh/zotmoov/master/updates.json",
      "parse_success": true
    },
    {
      "tag": "1.0.0.5",
      "published_at": "2024-08-03T17:45:22Z",
      "xpi_asset_id": 183675602,
      "xpi_name": "zotmoov-1.0.0.5-fx.xpi",
      "xpi_download_url": "https://github.com/wileyyugioh/zotmoov/releases/download/1.0.0.5/zotmoov-1.0.0.5-fx.xpi",
      "addon_id": "zotmoov@wileyy.com",
      "addon_name": "ZotMoov",
      "addon_version": "1.0.0.5",
      "addon_description": "Mooves attachments and links them",
      "min_zotero_version": "6.999",
      "max_zotero_version": "7.0.*",
      "update_url": "https://raw.githubusercontent.com/wileyyugioh/zotmoov/master/updates.json",
      "parse_success": true
    },
    {
      "tag": "1.0.0.4",
      "published_at": "2024-07-28T17:11:31Z",
      "xpi_asset_id": 182367334,
      "xpi_name": "zotmoov-1.0.0.4-fx.xpi",
      "xpi_download_url": "https://github.com/wileyyugioh/zotmoov/releases/download/1.0.0.4/zotmoov-1.0.0.4-fx.xpi",
      "addon_id": "zotmoov@wileyy.com",
      "addon_name": "ZotMoov",
      "addon_version": "1.0.0.4",
      "addon_description": "Mooves attachments and links them",
      "min_zotero_version": "6.999",
      "max_zotero_version": "7.0.*",
      "update_url": "https://raw.githubusercontent.com/wileyyugioh/zotmoov/master/updates.json",
      "parse_success": true
    },
    {
      "tag": "1.0.0.3",
      "published_at": "2024-07-26T06:44:02Z",
      "xpi_asset_id": 181951549,
      "xpi_name": "zotmoov-1.0.0.3-fx.xpi",
      "xpi_download_url": "https://github.com/wileyyugioh/zotmoov/releases/download/1.0.0.3/zotmoov-1.0.0.3-fx.xpi",
      "addon_id": "zotmoov@wileyy.com",
      "addon_name": "ZotMoov",
      "addon_version": "1.0.0.3",
      "addon_description": "Mooves attachments and links them",
      "min_zotero_version": "6.999",
      "max_zotero_version": "7.0.*",
      "update_url": "https://raw.githubusercontent.com/wileyyugioh/zotmoov/master/updates.json",
      "parse_success": true
    },
    {
      "tag": "1.0.0.2",
      "published_at": "2024-05-26T08:24:36Z",
      "xpi_asset_id": 170155537,
      "xpi_name": "zotmoov-1.0.0.2-fx.xpi",
      "xpi_download_url": "https://github.com/wileyyugioh/zotmoov/releases/download/1.0.0.2/zotmoov-1.0.0.2-fx.xpi",
      "addon_id": "zotmoov@wileyy.com",
      "addon_name": "ZotMoov",
      "addon_version": "1.0.0.2",
      "addon_description": "Mooves attachments and links them",
      "min_zotero_version": "6.999",
      "max_zotero_version": "7.0.*",
      "update_url": "https://raw.githubusercontent.com/wileyyugioh/zotmoov/master/updates.json",
      "parse_success": true
    },
    {
      "tag": "1.0.0.1",
      "published_at": "2024-05-17T03:52:30Z",
      "xpi_asset_id": 168427090,
      "xpi_name": "zotmoov-1.0.0.1-fx.xpi",
      "xpi_download_url": "https://github.com/wileyyugioh/zotmoov/releases/download/1.0.0.1/zotmoov-1.0.0.1-fx.xpi",
      "addon_id": "zotmoov@wileyy.com",
      "addon_name": "ZotMoov",
      "addon_version": "1.0.0.1",
      "addon_description": "Mooves attachments and links them",
      "min_zotero_version": "6.999",
      "max_zotero_version": "7.0.*",
      "update_url": "https://raw.githubusercontent.com/wileyyugioh/zotmoov/master/updates.json",
      "parse_success": true
    },
    {
      "tag": "1.0.0.0",
      "published_at": "2024-04-09T09:07:51Z",
      "xpi_asset_id": 161099625,
      "xpi_name": "zotmoov-1.0.0.0-fx.xpi",
      "xpi_download_url": "https://github.com/wileyyugioh/zotmoov/releases/download/1.0.0.0/zotmoov-1.0.0.0-fx.xpi",
      "addon_id": "zotmoov@wileyy.com",
      "addon_name": "ZotMoov",
      "addon_version": "1.0.0.0",
      "addon_description": "Mooves attachments and links them",
      "min_zotero_version": "6.999",
      "max_zotero_version": "7.0.*",
      "update_url": "https://raw.githubusercontent.com/wileyyugioh/zotmoov/master/updates.json",
      "parse_success": true
    },
    {
      "tag": "0.0.6b7",
      "published_at": "2024-04-02T03:28:17Z",
      "xpi_asset_id": 159806443,
      "xpi_name": "zotmoov-0.0.6b7-fx.xpi",
      "xpi_download_url": "https://github.com/wileyyugioh/zotmoov/releases/download/0.0.6b7/zotmoov-0.0.6b7-fx.xpi",
      "addon_id": "zotmoov@wileyy.com",
      "addon_name": "ZotMoov",
      "addon_version": "0.0.6b7",
      "addon_description": "Mooves attachments and links them",
      "min_zotero_version": "6.999",
      "max_zotero_version": "7.0.*",
      "update_url": "https://raw.githubusercontent.com/wileyyugioh/zotmoov/master/updates.json",
      "parse_success": true
    },
    {
      "tag": "0.0.6b6",
      "published_at": "2024-04-01T03:43:07Z",
      "xpi_asset_id": 159642207,
      "xpi_name": "zotmoov-0.0.6b6-fx.xpi",
      "xpi_download_url": "https://github.com/wileyyugioh/zotmoov/releases/download/0.0.6b6/zotmoov-0.0.6b6-fx.xpi",
      "addon_id": "zotmoov@wileyy.com",
      "addon_name": "ZotMoov",
      "addon_version": "0.0.6b6",
      "addon_description": "Mooves attachments and links them",
      "min_zotero_version": "6.999",
      "max_zotero_version": "7.0.*",
      "update_url": "https://raw.githubusercontent.com/wileyyugioh/zotmoov/master/updates.json",
      "parse_success": true
    },
    {
      "tag": "0.0.6b5",
      "published_at": "2024-03-28T22:31:59Z",
      "xpi_asset_id": 159172952,
      "xpi_name": "zotmoov-0.0.6b5-fx.xpi",
      "xpi_download_url": "https://github.com/wileyyugioh/zotmoov/releases/download/0.0.6b5/zotmoov-0.0.6b5-fx.xpi",
      "addon_id": "zotmoov@wileyy.com",
      "addon_name": "ZotMoov",
      "addon_version": "0.0.6b5",
      "addon_description": "Mooves attachments and links them",
      "min_zotero_version": "6.999",
      "max_zotero_version": "7.0.*",
      "update_url": "https://raw.githubusercontent.com/wileyyugioh/zotmoov/master/updates.json",
      "parse_success": true
    },
    {
      "tag": "0.0.6b4",
      "published_at": "2024-03-28T21:57:23Z",
      "xpi_asset_id": 159167431,
      "xpi_name": "zotmoov-0.0.6b4-fx.xpi",
      "xpi_download_url": "https://github.com/wileyyugioh/zotmoov/releases/download/0.0.6b4/zotmoov-0.0.6b4-fx.xpi",
      "addon_id": "zotmoov@wileyy.com",
      "addon_name": "ZotMoov",
      "addon_version": "0.0.6b4",
      "addon_description": "Mooves attachments and links them",
      "min_zotero_version": "6.999",
      "max_zotero_version": "7.0.*",
      "update_url": "https://raw.githubusercontent.com/wileyyugioh/zotmoov/master/updates.json",
      "parse_success": true
    },
    {
      "tag": "0.0.6b3",
      "published_at": "2024-03-28T21:29:34Z",
      "xpi_asset_id": 159164055,
      "xpi_name": "zotmoov-0.0.6b3-fx.xpi",
      "xpi_download_url": "https://github.com/wileyyugioh/zotmoov/releases/download/0.0.6b3/zotmoov-0.0.6b3-fx.xpi",
      "addon_id": "zotmoov@wileyy.com",
      "addon_name": "ZotMoov",
      "addon_version": "0.0.6b3",
      "addon_description": "Mooves attachments and links them",
      "min_zotero_version": "6.999",
      "max_zotero_version": "7.0.*",
      "update_url": "https://raw.githubusercontent.com/wileyyugioh/zotmoov/master/updates.json",
      "parse_success": true
    },
    {
      "tag": "0.0.6b2",
      "published_at": "2024-03-16T23:02:58Z",
      "xpi_asset_id": 157061237,
      "xpi_name": "zotmoov-0.0.6b2-fx.xpi",
      "xpi_download_url": "https://github.com/wileyyugioh/zotmoov/releases/download/0.0.6b2/zotmoov-0.0.6b2-fx.xpi",
      "addon_id": "zotmoov@wileyy.com",
      "addon_name": "ZotMoov",
      "addon_version": "0.0.6b2",
      "addon_description": "Mooves attachments and links them",
      "min_zotero_version": "6.999",
      "max_zotero_version": "7.0.*",
      "update_url": "https://raw.githubusercontent.com/wileyyugioh/zotmoov/master/updates.json",
      "parse_success": true
    },
    {
      "tag": "0.0.6b1",
      "published_at": "2024-03-16T01:07:43Z",
      "xpi_asset_id": 156947885,
      "xpi_name": "zotmoov-0.0.6b1-fx.xpi",
      "xpi_download_url": "https://github.com/wileyyugioh/zotmoov/releases/download/0.0.6b1/zotmoov-0.0.6b1-fx.xpi",
      "addon_id": "zotmoov@wileyy.com",
      "addon_name": "ZotMoov",
      "addon_version": "0.0.6b1",
      "addon_description": "Mooves attachments and links them",
      "min_zotero_version": "6.999",
      "max_zotero_version": "7.0.*",
      "update_url": "https://raw.githubusercontent.com/wileyyugioh/zotmoov/master/updates.json",
      "parse_success": true
    },
    {
      "tag": "0.0.5b7",
      "published_at": "2024-02-24T18:44:58Z",
      "xpi_asset_id": 153366575,
      "xpi_name": "zotmoov-0.0.5b7-fx.xpi",
      "xpi_download_url": "https://github.com/wileyyugioh/zotmoov/releases/download/0.0.5b7/zotmoov-0.0.5b7-fx.xpi",
      "addon_id": "zotmoov@wileyy.com",
      "addon_name": "ZotMoov",
      "addon_version": "0.0.5b7",
      "addon_description": "Mooves attachments and links them",
      "min_zotero_version": "6.999",
      "max_zotero_version": "7.0.*",
      "update_url": "https://raw.githubusercontent.com/wileyyugioh/zotmoov/master/updates.json",
      "parse_success": true
    },
    {
      "tag": "0.0.5b6",
      "published_at": "2024-02-23T09:39:58Z",
      "xpi_asset_id": 153148995,
      "xpi_name": "zotmoov-0.0.5b6-fx.xpi",
      "xpi_download_url": "https://github.com/wileyyugioh/zotmoov/releases/download/0.0.5b6/zotmoov-0.0.5b6-fx.xpi",
      "addon_id": "zotmoov@wileyy.com",
      "addon_name": "ZotMoov",
      "addon_version": "0.0.5b6",
      "addon_description": "Mooves attachments and links them",
      "min_zotero_version": "6.999",
      "max_zotero_version": "7.0.*",
      "update_url": "https://raw.githubusercontent.com/wileyyugioh/zotmoov/master/updates.json",
      "parse_success": true
    },
    {
      "tag": "0.0.5b5",
      "published_at": "2024-02-19T00:05:18Z",
      "xpi_asset_id": 152309729,
      "xpi_name": "zotmoov-0.0.5b5-fx.xpi",
      "xpi_download_url": "https://github.com/wileyyugioh/zotmoov/releases/download/0.0.5b5/zotmoov-0.0.5b5-fx.xpi",
      "addon_id": "zotmoov@wileyy.com",
      "addon_name": "ZotMoov",
      "addon_version": "0.0.5b5",
      "addon_description": "Mooves attachments and links them",
      "min_zotero_version": "6.999",
      "max_zotero_version": "7.0.*",
      "update_url": "https://raw.githubusercontent.com/wileyyugioh/zotmoov/master/updates.json",
      "parse_success": true
    },
    {
      "tag": "0.0.5b4",
      "published_at": "2024-02-18T01:38:39Z",
      "xpi_asset_id": 152161730,
      "xpi_name": "zotmoov-0.0.5b4-fx.xpi",
      "xpi_download_url": "https://github.com/wileyyugioh/zotmoov/releases/download/0.0.5b4/zotmoov-0.0.5b4-fx.xpi",
      "addon_id": "zotmoov@wileyy.com",
      "addon_name": "ZotMoov",
      "addon_version": "0.0.5b4",
      "addon_description": "Mooves attachments and links them",
      "min_zotero_version": "6.999",
      "max_zotero_version": "7.0.*",
      "update_url": "https://raw.githubusercontent.com/wileyyugioh/zotmoov/master/updates.json",
      "parse_success": true
    },
    {
      "tag": "0.0.5b3",
      "published_at": "2024-02-16T06:39:02Z",
      "xpi_asset_id": 151852798,
      "xpi_name": "zotmoov-0.0.5b3-fx.xpi",
      "xpi_download_url": "https://github.com/wileyyugioh/zotmoov/releases/download/0.0.5b3/zotmoov-0.0.5b3-fx.xpi",
      "addon_id": "zotmoov@wileyy.com",
      "addon_name": "ZotMoov",
      "addon_version": "0.0.5b3",
      "addon_description": "Mooves attachments and links them",
      "min_zotero_version": "6.999",
      "max_zotero_version": "7.0.*",
      "update_url": "https://raw.githubusercontent.com/wileyyugioh/zotmoov/master/updates.json",
      "parse_success": true
    },
    {
      "tag": "0.0.5b2",
      "published_at": "2024-02-16T06:32:40Z",
      "xpi_asset_id": 151852104,
      "xpi_name": "zotmoov-0.0.5b2-fx.xpi",
      "xpi_download_url": "https://github.com/wileyyugioh/zotmoov/releases/download/0.0.5b2/zotmoov-0.0.5b2-fx.xpi",
      "addon_id": "zotmoov@wileyy.com",
      "addon_name": "ZotMoov",
      "addon_version": "0.0.5b2",
      "addon_description": "Mooves attachments and links them",
      "min_zotero_version": "6.999",
      "max_zotero_version": "7.0.*",
      "update_url": "https://raw.githubusercontent.com/wileyyugioh/zotmoov/master/updates.json",
      "parse_success": true
    },
    {
      "tag": "0.0.5b1",
      "published_at": "2024-02-16T06:23:28Z",
      "xpi_asset_id": 151851356,
      "xpi_name": "zotmoov-0.0.5b1-fx.xpi",
      "xpi_download_url": "https://github.com/wileyyugioh/zotmoov/releases/download/0.0.5b1/zotmoov-0.0.5b1-fx.xpi",
      "addon_id": "zotmoov@wileyy.com",
      "addon_name": "ZotMoov",
      "addon_version": "0.0.5b1",
      "addon_description": "Mooves attachments and links them",
      "min_zotero_version": "6.999",
      "max_zotero_version": "7.0.*",
      "update_url": "https://raw.githubusercontent.com/wileyyugioh/zotmoov/master/updates.json",
      "parse_success": true
    },
    {
      "tag": "0.0.4b1",
      "published_at": "2024-01-10T08:35:18Z",
      "xpi_asset_id": 144770129,
      "xpi_name": "zotmoov-0.0.4b1-fx.xpi",
      "xpi_download_url": "https://github.com/wileyyugioh/zotmoov/releases/download/0.0.4b1/zotmoov-0.0.4b1-fx.xpi",
      "addon_id": "zotmoov@wileyy.com",
      "addon_name": "ZotMoov",
      "addon_version": "0.0.4b1",
      "addon_description": "Mooves attachments and links them",
      "min_zotero_version": "6.999",
      "max_zotero_version": "7.0.*",
      "update_url": "https://raw.githubusercontent.com/wileyyugioh/zotmoov/master/updates.json",
      "parse_success": true
    },
    {
      "tag": "0.0.3b7",
      "published_at": "2023-12-13T07:09:37Z",
      "xpi_asset_id": 140412998,
      "xpi_name": "zotmoov-0.0.3b7-fx.xpi",
      "xpi_download_url": "https://github.com/wileyyugioh/zotmoov/releases/download/0.0.3b7/zotmoov-0.0.3b7-fx.xpi",
      "addon_id": "zotmoov@wileyy.com",
      "addon_name": "ZotMoov",
      "addon_version": "0.0.3b7",
      "addon_description": "Mooves attachments and links them",
      "min_zotero_version": "6.999",
      "max_zotero_version": "7.0.*",
      "update_url": "https://raw.githubusercontent.com/wileyyugioh/zotmoov/master/updates.json",
      "parse_success": true
    },
    {
      "tag": "0.0.3b6",
      "published_at": "2023-11-21T17:56:34Z",
      "xpi_asset_id": 136742821,
      "xpi_name": "zotmoov-0.0.3b6-fx.xpi",
      "xpi_download_url": "https://github.com/wileyyugioh/zotmoov/releases/download/0.0.3b6/zotmoov-0.0.3b6-fx.xpi",
      "addon_id": "zotmoov@wileyy.com",
      "addon_name": "ZotMoov",
      "addon_version": "0.0.3b6",
      "addon_description": "Mooves attachments and links them",
      "min_zotero_version": "6.999",
      "max_zotero_version": "7.0.*",
      "update_url": "https://raw.githubusercontent.com/wileyyugioh/zotmoov/master/updates.json",
      "parse_success": true
    },
    {
      "tag": "0.0.3b5",
      "published_at": "2023-11-21T17:34:47Z",
      "xpi_asset_id": 136739745,
      "xpi_name": "zotmoov-0.0.3b5-fx.xpi",
      "xpi_download_url": "https://github.com/wileyyugioh/zotmoov/releases/download/0.0.3b5/zotmoov-0.0.3b5-fx.xpi",
      "addon_id": "zotmoov@wileyy.com",
      "addon_name": "ZotMoov",
      "addon_version": "0.0.3b5",
      "addon_description": "Mooves attachments and links them",
      "min_zotero_version": "6.999",
      "max_zotero_version": "7.0.*",
      "update_url": "https://raw.githubusercontent.com/wileyyugioh/zotmoov/master/updates.json",
      "parse_success": true
    },
    {
      "tag": "0.0.3b4",
      "published_at": "2023-11-21T17:05:47Z",
      "xpi_asset_id": 136736448,
      "xpi_name": "zotmoov-0.0.3b4-fx.xpi",
      "xpi_download_url": "https://github.com/wileyyugioh/zotmoov/releases/download/0.0.3b4/zotmoov-0.0.3b4-fx.xpi",
      "addon_id": "zotmoov@wileyy.com",
      "addon_name": "ZotMoov",
      "addon_version": "0.0.3b4",
      "addon_description": "Mooves attachments and links them",
      "min_zotero_version": "6.999",
      "max_zotero_version": "7.0.*",
      "update_url": "https://raw.githubusercontent.com/wileyyugioh/zotmoov/master/updates.json",
      "parse_success": true
    },
    {
      "tag": "0.0.3b3",
      "published_at": "2023-11-21T09:56:08Z",
      "xpi_asset_id": 136673974,
      "xpi_name": "zotmoov-0.0.3b3-fx.xpi",
      "xpi_download_url": "https://github.com/wileyyugioh/zotmoov/releases/download/0.0.3b3/zotmoov-0.0.3b3-fx.xpi",
      "addon_id": "zotmoov@wileyy.com",
      "addon_name": "ZotMoov",
      "addon_version": "0.0.3b3",
      "addon_description": "Mooves attachments and links them",
      "min_zotero_version": "6.999",
      "max_zotero_version": "7.0.*",
      "update_url": "https://raw.githubusercontent.com/wileyyugioh/zotmoov/master/updates.json",
      "parse_success": true
    },
    {
      "tag": "0.0.3b2",
      "published_at": "2023-11-10T10:21:43Z",
      "xpi_asset_id": 134883523,
      "xpi_name": "zotmoov-0.0.3b2-fx.xpi",
      "xpi_download_url": "https://github.com/wileyyugioh/zotmoov/releases/download/0.0.3b2/zotmoov-0.0.3b2-fx.xpi",
      "addon_id": "zotmoov@wileyy.com",
      "addon_name": "ZotMoov",
      "addon_version": "0.0.3b2",
      "addon_description": "Mooves attachments and links them",
      "min_zotero_version": "6.999",
      "max_zotero_version": "7.0.*",
      "update_url": "https://raw.githubusercontent.com/wileyyugioh/zotmoov/master/updates.json",
      "parse_success": true
    },
    {
      "tag": "0.0.3b1",
      "published_at": "2023-11-10T07:17:24Z",
      "xpi_asset_id": 134859680,
      "xpi_name": "zotmoov-0.0.3b1-fx.xpi",
      "xpi_download_url": "https://github.com/wileyyugioh/zotmoov/releases/download/0.0.3b1/zotmoov-0.0.3b1-fx.xpi",
      "addon_id": "zotmoov@wileyy.com",
      "addon_name": "ZotMoov",
      "addon_version": "0.0.3b1",
      "addon_description": "Mooves attachments and links them",
      "min_zotero_version": "6.999",
      "max_zotero_version": "7.0.*",
      "update_url": "https://raw.githubusercontent.com/wileyyugioh/zotmoov/master/updates.json",
      "parse_success": true
    },
    {
      "tag": "0.0.2b7",
      "published_at": "2023-10-18T05:06:13Z",
      "xpi_asset_id": 131128129,
      "xpi_name": "zotmoov-0.0.2b7-fx.xpi",
      "xpi_download_url": "https://github.com/wileyyugioh/zotmoov/releases/download/0.0.2b7/zotmoov-0.0.2b7-fx.xpi",
      "addon_id": "zotmoov@wileyy.com",
      "addon_name": "ZotMoov",
      "addon_version": "0.0.2b7",
      "addon_description": "Mooves attachments and links them",
      "min_zotero_version": "6.999",
      "max_zotero_version": "7.0.*",
      "update_url": "https://raw.githubusercontent.com/wileyyugioh/zotmoov/master/updates.json",
      "parse_success": true
    },
    {
      "tag": "0.0.2b6",
      "published_at": "2023-07-23T01:07:27Z",
      "xpi_asset_id": 118179627,
      "xpi_name": "zotmoov-0.0.2b6-fx.xpi",
      "xpi_download_url": "https://github.com/wileyyugioh/zotmoov/releases/download/0.0.2b6/zotmoov-0.0.2b6-fx.xpi",
      "addon_id": "zotmoov@wileyy.com",
      "addon_name": "ZotMoov",
      "addon_version": "0.0.2b6",
      "addon_description": "Mooves attachments and links them",
      "min_zotero_version": "6.999",
      "max_zotero_version": "7.0.*",
      "update_url": "https://raw.githubusercontent.com/wileyyugioh/zotmoov/master/updates.json",
      "parse_success": true
    },
    {
      "tag": "0.0.2b5",
      "published_at": "2023-07-22T22:13:42Z",
      "xpi_asset_id": 118163986,
      "xpi_name": "zotmoov-0.0.2b5-fx.xpi",
      "xpi_download_url": "https://github.com/wileyyugioh/zotmoov/releases/download/0.0.2b5/zotmoov-0.0.2b5-fx.xpi",
      "addon_id": "zotmoov@wileyy.com",
      "addon_name": "ZotMoov",
      "addon_version": "0.0.2b5",
      "addon_description": "Mooves attachments and links them",
      "min_zotero_version": "6.999",
      "max_zotero_version": "7.0.*",
      "update_url": "https://raw.githubusercontent.com/wileyyugioh/zotmoov/master/updates.json",
      "parse_success": true
    },
    {
      "tag": "0.0.2b4",
      "published_at": "2023-07-17T07:10:12Z",
      "xpi_asset_id": 117328850,
      "xpi_name": "zotmoov-0.0.2b4-fx.xpi",
      "xpi_download_url": "https://github.com/wileyyugioh/zotmoov/releases/download/0.0.2b4/zotmoov-0.0.2b4-fx.xpi",
      "addon_id": "zotmoov@wileyy.com",
      "addon_name": "ZotMoov",
      "addon_version": "0.0.2b4",
      "addon_description": "Mooves attachments and links them",
      "min_zotero_version": "6.999",
      "max_zotero_version": "7.0.*",
      "update_url": "https://raw.githubusercontent.com/wileyyugioh/zotmoov/master/updates.json",
      "parse_success": true
    },
    {
      "tag": "0.0.2b3",
      "published_at": "2023-07-15T10:23:48Z",
      "xpi_asset_id": 117126563,
      "xpi_name": "zotmoov-0.0.2b3-fx.xpi",
      "xpi_download_url": "https://github.com/wileyyugioh/zotmoov/releases/download/0.0.2b3/zotmoov-0.0.2b3-fx.xpi",
      "addon_id": "zotmoov@wileyy.com",
      "addon_name": "ZotMoov",
      "addon_version": "0.0.2b3",
      "addon_description": "Mooves attachments and links them",
      "min_zotero_version": "6.999",
      "max_zotero_version": "7.0.*",
      "update_url": "https://raw.githubusercontent.com/wileyyugioh/zotmoov/master/updates.json",
      "parse_success": true
    },
    {
      "tag": "0.0.2b2",
      "published_at": "2023-07-14T23:02:50Z",
      "xpi_asset_id": 117065482,
      "xpi_name": "zotmoov-0.0.2b2-fx.xpi",
      "xpi_download_url": "https://github.com/wileyyugioh/zotmoov/releases/download/0.0.2b2/zotmoov-0.0.2b2-fx.xpi",
      "addon_id": "zotmoov@wileyy.com",
      "addon_name": "ZotMoov",
      "addon_version": "0.0.2b2",
      "addon_description": "Mooves attachments and links them",
      "min_zotero_version": "6.999",
      "max_zotero_version": "7.0.*",
      "update_url": "https://raw.githubusercontent.com/wileyyugioh/zotmoov/master/updates.json",
      "parse_success": true
    },
    {
      "tag": "0.0.2b",
      "published_at": "2023-07-14T04:28:22Z",
      "xpi_asset_id": 116939370,
      "xpi_name": "zotmoov-0.0.2b-fx.xpi",
      "xpi_download_url": "https://github.com/wileyyugioh/zotmoov/releases/download/0.0.2b/zotmoov-0.0.2b-fx.xpi",
      "addon_id": "zotmoov@wileyy.com",
      "addon_name": "ZotMoov",
      "addon_version": "0.0.2b",
      "addon_description": "Mooves attachments and links them",
      "min_zotero_version": "6.999",
      "max_zotero_version": "7.0.*",
      "update_url": "https://raw.githubusercontent.com/wileyyugioh/zotmoov/master/updates.json",
      "parse_success": true
    },
    {
      "tag": "0.0.1b",
      "published_at": "2023-06-27T00:02:52Z",
      "xpi_asset_id": 114464522,
      "xpi_name": "zotmoov-0.0.1b-fx.xpi",
      "xpi_download_url": "https://github.com/wileyyugioh/zotmoov/releases/download/0.0.1b/zotmoov-0.0.1b-fx.xpi",
      "addon_id": "zotmoov@wileyy.com",
      "addon_name": "ZotMoov",
      "addon_version": "0.0.1b",
      "addon_description": "Mooves attachments and links them",
      "min_zotero_version": "6.999",
      "max_zotero_version": "7.0.*",
      "update_url": "https://raw.githubusercontent.com/wileyyugioh/zotmoov/master/updates.json",
      "parse_success": true
    },
    {
      "tag": "1.2.27",
      "published_at": "2026-01-28T06:30:53Z",
      "xpi_asset_id": 347023184,
      "xpi_name": "zotmoov-1.2.27-fx.xpi",
      "xpi_download_url": "https://github.com/wileyyugioh/zotmoov/releases/download/1.2.27/zotmoov-1.2.27-fx.xpi",
      "addon_id": "zotmoov@wileyy.com",
      "addon_name": "ZotMoov",
      "addon_version": "1.2.27",
      "addon_description": "Mooves attachments and links them",
      "min_zotero_version": "6.999",
      "max_zotero_version": "8.0.*",
      "update_url": "https://raw.githubusercontent.com/wileyyugioh/zotmoov/master/updates.json",
      "parse_success": true
    }
  ]
}